AUTHORS
ChangeLog
MANIFEST.in
README.rst
requirements.txt
setup.cfg
setup.py
leonardo_system/.gitignore
leonardo_system/__init__.py
leonardo_system/settings.py
leonardo_system/urls.py
leonardo_system.egg-info/PKG-INFO
leonardo_system.egg-info/SOURCES.txt
leonardo_system.egg-info/dependency_links.txt
leonardo_system.egg-info/not-zip-safe
leonardo_system.egg-info/pbr.json
leonardo_system.egg-info/requires.txt
leonardo_system.egg-info/top_level.txt
leonardo_system/locale/cs/LC_MESSAGES/django.mo
leonardo_system/locale/cs/LC_MESSAGES/django.po
leonardo_system/locale/de/LC_MESSAGES/django.po
leonardo_system/locale/en/LC_MESSAGES/django.po
leonardo_system/locale/es/LC_MESSAGES/django.po
leonardo_system/locale/nl/LC_MESSAGES/django.po
leonardo_system/locale/pl/LC_MESSAGES/django.po
leonardo_system/locale/sk/LC_MESSAGES/django.po
leonardo_system/maintenance/__init__.py
leonardo_system/maintenance/forms.py
leonardo_system/maintenance/tables.py
leonardo_system/maintenance/urls.py
leonardo_system/maintenance/views.py
leonardo_system/management/__init__.py
leonardo_system/management/commands/__init__.py
leonardo_system/management/commands/_utils.py
leonardo_system/management/commands/system_check.py
leonardo_system/management/commands/system_update.py
leonardo_system/package/__init__.py
leonardo_system/package/forms.py
leonardo_system/package/patch_pip.py
leonardo_system/package/urls.py
leonardo_system/package/utils.py
leonardo_system/package/views.py
leonardo_system/pip/__init__.py
leonardo_system/pip/versions.py
leonardo_system/templates/system/module_actions.html
requirements/default.txt